{
  "event_id": "UFC_303",
  "event_name": "UFC 303",
  "event_date": "2024-06-29",
  "venue": "T-Mobile Arena",
  "location": null,
  "status": "completed",
  "attendance": null,
  "gate": null,
  "tv_broadcast": null,
  "start_time": null,
  "fights": [
    {
      "bout_order": 13,
      "fighter1": {
        "name": "Alex Pereira",
        "record": null,
        "rank": null,
        "country": null,
        "age": null,
        "height": null,
        "weight": null,
        "reach": null,
        "stance": null,
        "nickname": null,
        "bonus": null,
        "is_champion": true
      },
      "fighter2": {
        "name": "Jiří Procházka",
        "record": null,
        "rank": null,
        "country": null,
        "age": null,
        "height": null,
        "weight": null,
        "reach": null,
        "stance": null,
        "nickname": null,
        "bonus": null,
        "is_champion": false
      },
      "weight_class": "Light Heavyweight",
      "title_fight": "undisputed",
      "method": "TKO (head kick and punches)",
      "round": null,
      "time": null,
      "winner": "Alex Pereira",
      "result": null,
      "stats": null,
      "referee": null,
      "bonuses": null,
      "fight_url": null,
      "segment": "main-card"
    },
    {
      "bout_order": 12,
      "fighter1": {
        "name": "Diego Lopes",
        "record": null,
        "rank": null,
        "country": null,
        "age": null,
        "height": null,
        "weight": null,
        "reach": null,
        "stance": null,
        "nickname": null,
        "bonus": null,
        "is_champion": false
      },
      "fighter2": {
        "name": "Dan Ige",
        "record": null,
        "rank": null,
        "country": null,
        "age": null,
        "height": null,
        "weight": null,
        "reach": null,
        "stance": null,
        "nickname": null,
        "bonus": null,
        "is_champion": false
      },
      "weight_class": "Catchweight (165 lb)",
      "title_fight": "none",
      "method": "Decision (unanimous) (29–28, 29–28, 29–28)",
      "round": null,
      "time": null,
      "winner": "Diego Lopes",
      "result": null,
      "stats": null,
      "referee": null,
      "bonuses": null,
      "fight_url": null,
      "segment": "main-card"
    },
    {
      "bout_order": 11,
      "fighter1": {
        "name": "Roman Dolidze",
        "record": null,
        "rank": null,
        "country": null,
        "age": null,
        "height": null,
        "weight": null,
        "reach": null,
        "stance": null,
        "nickname": null,
        "bonus": null,
        "is_champion": false
      },
      "fighter2": {
        "name": "Anthony Smith",
        "record": null,
        "rank": null,
        "country": null,
        "age": null,
        "height": null,
        "weight": null,
        "reach": null,
        "stance": null,
        "nickname": null,
        "bonus": null,
        "is_champion": false
      },
      "weight_class": "Light Heavyweight",
      "title_fight": "none",
      "method": "Decision (unanimous) (30–27, 29–28, 29–28)",
      "round": null,
      "time": null,
      "winner": "Roman Dolidze",
      "result": null,
      "stats": null,
      "referee": null,
      "bonuses": null,
      "fight_url": null,
      "segment": "main-card"
    },
    {
      "bout_order": 10,
      "fighter1": {
        "name": "Macy Chiasson",
        "record": null,
        "rank": null,
        "country": null,
        "age": null,
        "height": null,
        "weight": null,
        "reach": null,
        "stance": null,
        "nickname": null,
        "bonus": null,
        "is_champion": false
      },
      "fighter2": {
        "name": "Mayra Bueno Silva",
        "record": null,
        "rank": null,
        "country": null,
        "age": null,
        "height": null,
        "weight": null,
        "reach": null,
        "stance": null,
        "nickname": null,
        "bonus": null,
        "is_champion": false
      },
      "weight_class": "Women's Bantamweight",
      "title_fight": "none",
      "method": "TKO (doctor stoppage)",
      "round": null,
      "time": null,
      "winner": "Macy Chiasson",
      "result": null,
      "stats": null,
      "referee": null,
      "bonuses": null,
      "fight_url": null,
      "segment": "main-card"
    },
    {
      "bout_order": 9,
      "fighter1": {
        "name": "Ian Machado Garry",
        "record": null,
        "rank": null,
        "country": null,
        "age": null,
        "height": null,
        "weight": null,
        "reach": null,
        "stance": null,
        "nickname": null,
        "bonus": null,
        "is_champion": false
      },
      "fighter2": {
        "name": "Michael Page",
        "record": null,
        "rank": null,
        "country": null,
        "age": null,
        "height": null,
        "weight": null,
        "reach": null,
        "stance": null,
        "nickname": null,
        "bonus": null,
        "is_champion": false
      },
      "weight_class": "Welterweight",
      "title_fight": "none",
      "method": "Decision (unanimous) (29–28, 29–28, 29–28)",
      "round": null,
      "time": null,
      "winner": "Ian Machado Garry",
      "result": null,
      "stats": null,
      "referee": null,
      "bonuses": null,
      "fight_url": null,
      "segment": "main-card"
    },
    {
      "bout_order": 8,
      "fighter1": {
        "name": "Joe Pyfer",
        "record": null,
        "rank": null,
        "country": null,
        "age": null,
        "height": null,
        "weight": null,
        "reach": null,
        "stance": null,
        "nickname": null,
        "bonus": null,
        "is_champion": false
      },
      "fighter2": {
        "name": "Marc-André Barriault",
        "record": null,
        "rank": null,
        "country": null,
        "age": null,
        "height": null,
        "weight": null,
        "reach": null,
        "stance": null,
        "nickname": null,
        "bonus": null,
        "is_champion": false
      },
      "weight_class": "Middleweight",
      "title_fight": "none",
      "method": "KO (punches)",
      "round": null,
      "time": null,
      "winner": "Joe Pyfer",
      "result": null,
      "stats": null,
      "referee": null,
      "bonuses": null,
      "fight_url": null,
      "segment": "prelims"
    },
    {
      "bout_order": 7,
      "fighter1": {
        "name": "Andre Fili",
        "record": null,
        "rank": null,
        "country": null,
        "age": null,
        "height": null,
        "weight": null,
        "reach": null,
        "stance": null,
        "nickname": null,
        "bonus": null,
        "is_champion": false
      },
      "fighter2": {
        "name": "Cub Swanson",
        "record": null,
        "rank": null,
        "country": null,
        "age": null,
        "height": null,
        "weight": null,
        "reach": null,
        "stance": null,
        "nickname": null,
        "bonus": null,
        "is_champion": false
      },
      "weight_class": "Featherweight",
      "title_fight": "none",
      "method": "Decision (split) (28–29, 29–28, 29–28)",
      "round": null,
      "time": null,
      "winner": "Andre Fili",
      "result": null,
      "stats": null,
      "referee": null,
      "bonuses": null,
      "fight_url": null,
      "segment": "prelims"
    },
    {
      "bout_order": 6,
      "fighter1": {
        "name": "Jean Silva",
        "record": null,
        "rank": null,
        "country": null,
        "age": null,
        "height": null,
        "weight": null,
        "reach": null,
        "stance": null,
        "nickname": null,
        "bonus": null,
        "is_champion": false
      },
      "fighter2": {
        "name": "Charles Jourdain",
        "record": null,
        "rank": null,
        "country": null,
        "age": null,
        "height": null,
        "weight": null,
        "reach": null,
        "stance": null,
        "nickname": null,
        "bonus": null,
        "is_champion": false
      },
      "weight_class": "Catchweight (147.5 lb)",
      "title_fight": "none",
      "method": "KO (punch)",
      "round": null,
      "time": null,
      "winner": "Jean Silva",
      "result": null,
      "stats": null,
      "referee": null,
      "bonuses": null,
      "fight_url": null,
      "segment": "prelims"
    },
    {
      "bout_order": 5,
      "fighter1": {
        "name": "Payton Talbott",
        "record": null,
        "rank": null,
        "country": null,
        "age": null,
        "height": null,
        "weight": null,
        "reach": null,
        "stance": null,
        "nickname": null,
        "bonus": null,
        "is_champion": false
      },
      "fighter2": {
        "name": "Yanis Ghemmouri",
        "record": null,
        "rank": null,
        "country": null,
        "age": null,
        "height": null,
        "weight": null,
        "reach": null,
        "stance": null,
        "nickname": null,
        "bonus": null,
        "is_champion": false
      },
      "weight_class": "Bantamweight",
      "title_fight": "none",
      "method": "KO (punches)",
      "round": null,
      "time": null,
      "winner": "Payton Talbott",
      "result": null,
      "stats": null,
      "referee": null,
      "bonuses": null,
      "fight_url": null,
      "segment": "prelims"
    },
    {
      "bout_order": 4,
      "fighter1": {
        "name": "Gillian Robertson",
        "record": null,
        "rank": null,
        "country": null,
        "age": null,
        "height": null,
        "weight": null,
        "reach": null,
        "stance": null,
        "nickname": null,
        "bonus": null,
        "is_champion": false
      },
      "fighter2": {
        "name": "Michelle Waterson-Gomez",
        "record": null,
        "rank": null,
        "country": null,
        "age": null,
        "height": null,
        "weight": null,
        "reach": null,
        "stance": null,
        "nickname": null,
        "bonus": null,
        "is_champion": false
      },
      "weight_class": "Women's Strawweight",
      "title_fight": "none",
      "method": "Decision (unanimous) (30–27, 30–27, 30–26)",
      "round": null,
      "time": null,
      "winner": "Gillian Robertson",
      "result": null,
      "stats": null,
      "referee": null,
      "bonuses": null,
      "fight_url": null,
      "segment": "early-prelims"
    },
    {
      "bout_order": 3,
      "fighter1": {
        "name": "Martin Buday",
        "record": null,
        "rank": null,
        "country": null,
        "age": null,
        "height": null,
        "weight": null,
        "reach": null,
        "stance": null,
        "nickname": null,
        "bonus": null,
        "is_champion": false
      },
      "fighter2": {
        "name": "Andrei Arlovski",
        "record": null,
        "rank": null,
        "country": null,
        "age": null,
        "height": null,
        "weight": null,
        "reach": null,
        "stance": null,
        "nickname": null,
        "bonus": null,
        "is_champion": false
      },
      "weight_class": "Heavyweight",
      "title_fight": "none",
      "method": "Decision (split) (29–28, 28–29, 30–27)",
      "round": null,
      "time": null,
      "winner": "Martin Buday",
      "result": null,
      "stats": null,
      "referee": null,
      "bonuses": null,
      "fight_url": null,
      "segment": "early-prelims"
    },
    {
      "bout_order": 2,
      "fighter1": {
        "name": "Rei Tsuruya",
        "record": null,
        "rank": null,
        "country": null,
        "age": null,
        "height": null,
        "weight": null,
        "reach": null,
        "stance": null,
        "nickname": null,
        "bonus": null,
        "is_champion": false
      },
      "fighter2": {
        "name": "Carlos Hernandez",
        "record": null,
        "rank": null,
        "country": null,
        "age": null,
        "height": null,
        "weight": null,
        "reach": null,
        "stance": null,
        "nickname": null,
        "bonus": null,
        "is_champion": false
      },
      "weight_class": "Flyweight",
      "title_fight": "none",
      "method": "Decision (unanimous) (29–28, 29–28, 29–28)",
      "round": null,
      "time": null,
      "winner": "Rei Tsuruya",
      "result": null,
      "stats": null,
      "referee": null,
      "bonuses": null,
      "fight_url": null,
      "segment": "early-prelims"
    },
    {
      "bout_order": 1,
      "fighter1": {
        "name": "Vinicius Oliveira",
        "record": null,
        "rank": null,
        "country": null,
        "age": null,
        "height": null,
        "weight": null,
        "reach": null,
        "stance": null,
        "nickname": null,
        "bonus": null,
        "is_champion": false
      },
      "fighter2": {
        "name": "Ricky Simón",
        "record": null,
        "rank": null,
        "country": null,
        "age": null,
        "height": null,
        "weight": null,
        "reach": null,
        "stance": null,
        "nickname": null,
        "bonus": null,
        "is_champion": false
      },
      "weight_class": "Bantamweight",
      "title_fight": "none",
      "method": "Decision (unanimous) (30–27, 30–27, 29–28)",
      "round": null,
      "time": null,
      "winner": "Vinicius Oliveira",
      "result": null,
      "stats": null,
      "referee": null,
      "bonuses": null,
      "fight_url": null,
      "segment": "early-prelims"
    }
  ],
  "scraped_at": "2025-07-13T11:54:36.254769",
  "source_urls": {
    "wikipedia": "https://en.wikipedia.org/wiki/UFC_303"
  }
}