{
  "event_id": "UFC_293",
  "event_name": "UFC 293",
  "event_date": "2023-09-10",
  "venue": "Qudos Bank Arena",
  "location": null,
  "status": "completed",
  "attendance": null,
  "gate": null,
  "tv_broadcast": null,
  "start_time": null,
  "fights": [
    {
      "bout_order": 12,
      "fighter1": {
        "name": "Sean Strickland",
        "record": null,
        "rank": null,
        "country": null,
        "age": null,
        "height": null,
        "weight": null,
        "reach": null,
        "stance": null,
        "nickname": null,
        "bonus": null
      },
      "fighter2": {
        "name": "Israel Adesanya",
        "record": null,
        "rank": null,
        "country": null,
        "age": null,
        "height": null,
        "weight": null,
        "reach": null,
        "stance": null,
        "nickname": null,
        "bonus": null
      },
      "weight_class": "Middleweight",
      "title_fight": "none",
      "method": "Decision (unanimous) (49–46, 49–46, 49–46)",
      "round": null,
      "time": null,
      "winner": "Sean Strickland",
      "result": null,
      "stats": null,
      "referee": null,
      "bonuses": null,
      "fight_url": null,
      "segment": "main-card"
    },
    {
      "bout_order": 11,
      "fighter1": {
        "name": "Alexander Volkov",
        "record": null,
        "rank": null,
        "country": null,
        "age": null,
        "height": null,
        "weight": null,
        "reach": null,
        "stance": null,
        "nickname": null,
        "bonus": null
      },
      "fighter2": {
        "name": "Tai Tuivasa",
        "record": null,
        "rank": null,
        "country": null,
        "age": null,
        "height": null,
        "weight": null,
        "reach": null,
        "stance": null,
        "nickname": null,
        "bonus": null
      },
      "weight_class": "Heavyweight",
      "title_fight": "none",
      "method": "Submission (Ezekiel choke)",
      "round": null,
      "time": null,
      "winner": "Alexander Volkov",
      "result": null,
      "stats": null,
      "referee": null,
      "bonuses": null,
      "fight_url": null,
      "segment": "main-card"
    },
    {
      "bout_order": 10,
      "fighter1": {
        "name": "Manel Kape",
        "record": null,
        "rank": null,
        "country": null,
        "age": null,
        "height": null,
        "weight": null,
        "reach": null,
        "stance": null,
        "nickname": null,
        "bonus": null
      },
      "fighter2": {
        "name": "Felipe dos Santos",
        "record": null,
        "rank": null,
        "country": null,
        "age": null,
        "height": null,
        "weight": null,
        "reach": null,
        "stance": null,
        "nickname": null,
        "bonus": null
      },
      "weight_class": "Flyweight",
      "title_fight": "none",
      "method": "Decision (unanimous) (30–27, 29–28, 29–28)",
      "round": null,
      "time": null,
      "winner": "Manel Kape",
      "result": null,
      "stats": null,
      "referee": null,
      "bonuses": null,
      "fight_url": null,
      "segment": "main-card"
    },
    {
      "bout_order": 9,
      "fighter1": {
        "name": "Justin Tafa",
        "record": null,
        "rank": null,
        "country": null,
        "age": null,
        "height": null,
        "weight": null,
        "reach": null,
        "stance": null,
        "nickname": null,
        "bonus": null
      },
      "fighter2": {
        "name": "Austen Lane",
        "record": null,
        "rank": null,
        "country": null,
        "age": null,
        "height": null,
        "weight": null,
        "reach": null,
        "stance": null,
        "nickname": null,
        "bonus": null
      },
      "weight_class": "Heavyweight",
      "title_fight": "none",
      "method": "KO (punches)",
      "round": null,
      "time": null,
      "winner": "Justin Tafa",
      "result": null,
      "stats": null,
      "referee": null,
      "bonuses": null,
      "fight_url": null,
      "segment": "main-card"
    },
    {
      "bout_order": 8,
      "fighter1": {
        "name": "Tyson Pedro",
        "record": null,
        "rank": null,
        "country": null,
        "age": null,
        "height": null,
        "weight": null,
        "reach": null,
        "stance": null,
        "nickname": null,
        "bonus": null
      },
      "fighter2": {
        "name": "Anton Turkalj",
        "record": null,
        "rank": null,
        "country": null,
        "age": null,
        "height": null,
        "weight": null,
        "reach": null,
        "stance": null,
        "nickname": null,
        "bonus": null
      },
      "weight_class": "Light Heavyweight",
      "title_fight": "none",
      "method": "KO (punches)",
      "round": null,
      "time": null,
      "winner": "Tyson Pedro",
      "result": null,
      "stats": null,
      "referee": null,
      "bonuses": null,
      "fight_url": null,
      "segment": "main-card"
    },
    {
      "bout_order": 7,
      "fighter1": {
        "name": "Carlos Ulberg",
        "record": null,
        "rank": null,
        "country": null,
        "age": null,
        "height": null,
        "weight": null,
        "reach": null,
        "stance": null,
        "nickname": null,
        "bonus": null
      },
      "fighter2": {
        "name": "Jung Da-un",
        "record": null,
        "rank": null,
        "country": null,
        "age": null,
        "height": null,
        "weight": null,
        "reach": null,
        "stance": null,
        "nickname": null,
        "bonus": null
      },
      "weight_class": "Light Heavyweight",
      "title_fight": "none",
      "method": "Submission (rear-naked choke)",
      "round": null,
      "time": null,
      "winner": "Carlos Ulberg",
      "result": null,
      "stats": null,
      "referee": null,
      "bonuses": null,
      "fight_url": null,
      "segment": "prelims"
    },
    {
      "bout_order": 6,
      "fighter1": {
        "name": "Chepe Mariscal",
        "record": null,
        "rank": null,
        "country": null,
        "age": null,
        "height": null,
        "weight": null,
        "reach": null,
        "stance": null,
        "nickname": null,
        "bonus": null
      },
      "fighter2": {
        "name": "Jack Jenkins",
        "record": null,
        "rank": null,
        "country": null,
        "age": null,
        "height": null,
        "weight": null,
        "reach": null,
        "stance": null,
        "nickname": null,
        "bonus": null
      },
      "weight_class": "Featherweight",
      "title_fight": "none",
      "method": "TKO (arm injury)",
      "round": null,
      "time": null,
      "winner": "Chepe Mariscal",
      "result": null,
      "stats": null,
      "referee": null,
      "bonuses": null,
      "fight_url": null,
      "segment": "prelims"
    },
    {
      "bout_order": 5,
      "fighter1": {
        "name": "Jamie Mullarkey",
        "record": null,
        "rank": null,
        "country": null,
        "age": null,
        "height": null,
        "weight": null,
        "reach": null,
        "stance": null,
        "nickname": null,
        "bonus": null
      },
      "fighter2": {
        "name": "John Makdessi",
        "record": null,
        "rank": null,
        "country": null,
        "age": null,
        "height": null,
        "weight": null,
        "reach": null,
        "stance": null,
        "nickname": null,
        "bonus": null
      },
      "weight_class": "Lightweight",
      "title_fight": "none",
      "method": "Decision (unanimous) (29–28, 29–28, 29–28)",
      "round": null,
      "time": null,
      "winner": "Jamie Mullarkey",
      "result": null,
      "stats": null,
      "referee": null,
      "bonuses": null,
      "fight_url": null,
      "segment": "prelims"
    },
    {
      "bout_order": 4,
      "fighter1": {
        "name": "Nasrat Haqparast",
        "record": null,
        "rank": null,
        "country": null,
        "age": null,
        "height": null,
        "weight": null,
        "reach": null,
        "stance": null,
        "nickname": null,
        "bonus": null
      },
      "fighter2": {
        "name": "Landon Quiñones",
        "record": null,
        "rank": null,
        "country": null,
        "age": null,
        "height": null,
        "weight": null,
        "reach": null,
        "stance": null,
        "nickname": null,
        "bonus": null
      },
      "weight_class": "Lightweight",
      "title_fight": "none",
      "method": "Decision (unanimous) (30–27, 30–27, 30–27)",
      "round": null,
      "time": null,
      "winner": "Nasrat Haqparast",
      "result": null,
      "stats": null,
      "referee": null,
      "bonuses": null,
      "fight_url": null,
      "segment": "prelims"
    },
    {
      "bout_order": 3,
      "fighter1": {
        "name": "Charlie Radtke",
        "record": null,
        "rank": null,
        "country": null,
        "age": null,
        "height": null,
        "weight": null,
        "reach": null,
        "stance": null,
        "nickname": null,
        "bonus": null
      },
      "fighter2": {
        "name": "Mike Mathetha",
        "record": null,
        "rank": null,
        "country": null,
        "age": null,
        "height": null,
        "weight": null,
        "reach": null,
        "stance": null,
        "nickname": null,
        "bonus": null
      },
      "weight_class": "Welterweight",
      "title_fight": "none",
      "method": "Decision (unanimous) (29–27, 29–27, 29–27)",
      "round": null,
      "time": null,
      "winner": "Charlie Radtke",
      "result": null,
      "stats": null,
      "referee": null,
      "bonuses": null,
      "fight_url": null,
      "segment": "early-prelims"
    },
    {
      "bout_order": 2,
      "fighter1": {
        "name": "Gabriel Miranda",
        "record": null,
        "rank": null,
        "country": null,
        "age": null,
        "height": null,
        "weight": null,
        "reach": null,
        "stance": null,
        "nickname": null,
        "bonus": null
      },
      "fighter2": {
        "name": "Shane Young",
        "record": null,
        "rank": null,
        "country": null,
        "age": null,
        "height": null,
        "weight": null,
        "reach": null,
        "stance": null,
        "nickname": null,
        "bonus": null
      },
      "weight_class": "Catchweight (149.75 lb)",
      "title_fight": "none",
      "method": "Technical Submission (rear-naked choke)",
      "round": null,
      "time": null,
      "winner": "Gabriel Miranda",
      "result": null,
      "stats": null,
      "referee": null,
      "bonuses": null,
      "fight_url": null,
      "segment": "early-prelims"
    },
    {
      "bout_order": 1,
      "fighter1": {
        "name": "Kevin Jousset",
        "record": null,
        "rank": null,
        "country": null,
        "age": null,
        "height": null,
        "weight": null,
        "reach": null,
        "stance": null,
        "nickname": null,
        "bonus": null
      },
      "fighter2": {
        "name": "Kiefer Crosbie",
        "record": null,
        "rank": null,
        "country": null,
        "age": null,
        "height": null,
        "weight": null,
        "reach": null,
        "stance": null,
        "nickname": null,
        "bonus": null
      },
      "weight_class": "Welterweight",
      "title_fight": "none",
      "method": "Submission (rear-naked choke)",
      "round": null,
      "time": null,
      "winner": "Kevin Jousset",
      "result": null,
      "stats": null,
      "referee": null,
      "bonuses": null,
      "fight_url": null,
      "segment": "early-prelims"
    }
  ],
  "scraped_at": "2025-07-12T22:38:52.641130",
  "source_urls": {
    "wikipedia": "https://en.wikipedia.org/wiki/UFC_293"
  }
}