{
  "event_id": "UFC_on_ESPN:_Strickland_vs._Magomedov",
  "event_name": "UFC on ESPN: Strickland vs. Magomedov",
  "event_date": "2023-07-01",
  "venue": "UFC Apex",
  "location": null,
  "status": "completed",
  "attendance": null,
  "gate": null,
  "tv_broadcast": null,
  "start_time": null,
  "fights": [
    {
      "bout_order": 12,
      "fighter1": {
        "name": "Sean Strickland",
        "record": null,
        "rank": null,
        "country": null,
        "age": null,
        "height": null,
        "weight": null,
        "reach": null,
        "stance": null,
        "nickname": null,
        "bonus": null
      },
      "fighter2": {
        "name": "Abusupiyan Magomedov",
        "record": null,
        "rank": null,
        "country": null,
        "age": null,
        "height": null,
        "weight": null,
        "reach": null,
        "stance": null,
        "nickname": null,
        "bonus": null
      },
      "weight_class": "Middleweight",
      "title_fight": "none",
      "method": "TKO (punches)",
      "round": null,
      "time": null,
      "winner": "Sean Strickland",
      "result": null,
      "stats": null,
      "referee": null,
      "bonuses": null,
      "fight_url": null,
      "segment": "main-card"
    },
    {
      "bout_order": 11,
      "fighter1": {
        "name": "Grant Dawson",
        "record": null,
        "rank": null,
        "country": null,
        "age": null,
        "height": null,
        "weight": null,
        "reach": null,
        "stance": null,
        "nickname": null,
        "bonus": null
      },
      "fighter2": {
        "name": "Damir Ismagulov",
        "record": null,
        "rank": null,
        "country": null,
        "age": null,
        "height": null,
        "weight": null,
        "reach": null,
        "stance": null,
        "nickname": null,
        "bonus": null
      },
      "weight_class": "Lightweight",
      "title_fight": "none",
      "method": "Decision (unanimous) (30–26, 30–27, 30–27)",
      "round": null,
      "time": null,
      "winner": "Grant Dawson",
      "result": null,
      "stats": null,
      "referee": null,
      "bonuses": null,
      "fight_url": null,
      "segment": "main-card"
    },
    {
      "bout_order": 10,
      "fighter1": {
        "name": "Michael Morales",
        "record": null,
        "rank": null,
        "country": null,
        "age": null,
        "height": null,
        "weight": null,
        "reach": null,
        "stance": null,
        "nickname": null,
        "bonus": null
      },
      "fighter2": {
        "name": "Max Griffin",
        "record": null,
        "rank": null,
        "country": null,
        "age": null,
        "height": null,
        "weight": null,
        "reach": null,
        "stance": null,
        "nickname": null,
        "bonus": null
      },
      "weight_class": "Welterweight",
      "title_fight": "none",
      "method": "Decision (unanimous) (29–28, 29–28, 29–28)",
      "round": null,
      "time": null,
      "winner": "Michael Morales",
      "result": null,
      "stats": null,
      "referee": null,
      "bonuses": null,
      "fight_url": null,
      "segment": "main-card"
    },
    {
      "bout_order": 9,
      "fighter1": {
        "name": "Ariane Lipski",
        "record": null,
        "rank": null,
        "country": null,
        "age": null,
        "height": null,
        "weight": null,
        "reach": null,
        "stance": null,
        "nickname": null,
        "bonus": null
      },
      "fighter2": {
        "name": "Melissa Gatto",
        "record": null,
        "rank": null,
        "country": null,
        "age": null,
        "height": null,
        "weight": null,
        "reach": null,
        "stance": null,
        "nickname": null,
        "bonus": null
      },
      "weight_class": "Women's Flyweight",
      "title_fight": "none",
      "method": "Decision (split) (28–29, 30–27, 29–28)",
      "round": null,
      "time": null,
      "winner": "Ariane Lipski",
      "result": null,
      "stats": null,
      "referee": null,
      "bonuses": null,
      "fight_url": null,
      "segment": "main-card"
    },
    {
      "bout_order": 8,
      "fighter1": {
        "name": "Benoît Saint Denis",
        "record": null,
        "rank": null,
        "country": null,
        "age": null,
        "height": null,
        "weight": null,
        "reach": null,
        "stance": null,
        "nickname": null,
        "bonus": null
      },
      "fighter2": {
        "name": "Ismael Bonfim",
        "record": null,
        "rank": null,
        "country": null,
        "age": null,
        "height": null,
        "weight": null,
        "reach": null,
        "stance": null,
        "nickname": null,
        "bonus": null
      },
      "weight_class": "Lightweight",
      "title_fight": "none",
      "method": "Submission (rear-naked choke)",
      "round": null,
      "time": null,
      "winner": "Benoît Saint Denis",
      "result": null,
      "stats": null,
      "referee": null,
      "bonuses": null,
      "fight_url": null,
      "segment": "main-card"
    },
    {
      "bout_order": 7,
      "fighter1": {
        "name": "Nursulton Ruziboev",
        "record": null,
        "rank": null,
        "country": null,
        "age": null,
        "height": null,
        "weight": null,
        "reach": null,
        "stance": null,
        "nickname": null,
        "bonus": null
      },
      "fighter2": {
        "name": "Brunno Ferreira",
        "record": null,
        "rank": null,
        "country": null,
        "age": null,
        "height": null,
        "weight": null,
        "reach": null,
        "stance": null,
        "nickname": null,
        "bonus": null
      },
      "weight_class": "Middleweight",
      "title_fight": "none",
      "method": "KO (punches)",
      "round": null,
      "time": null,
      "winner": "Nursulton Ruziboev",
      "result": null,
      "stats": null,
      "referee": null,
      "bonuses": null,
      "fight_url": null,
      "segment": "main-card"
    },
    {
      "bout_order": 6,
      "fighter1": {
        "name": "Rinat Fakhretdinov",
        "record": null,
        "rank": null,
        "country": null,
        "age": null,
        "height": null,
        "weight": null,
        "reach": null,
        "stance": null,
        "nickname": null,
        "bonus": null
      },
      "fighter2": {
        "name": "Kevin Lee",
        "record": null,
        "rank": null,
        "country": null,
        "age": null,
        "height": null,
        "weight": null,
        "reach": null,
        "stance": null,
        "nickname": null,
        "bonus": null
      },
      "weight_class": "Welterweight",
      "title_fight": "none",
      "method": "Technical Submission (guillotine choke)",
      "round": null,
      "time": null,
      "winner": "Rinat Fakhretdinov",
      "result": null,
      "stats": null,
      "referee": null,
      "bonuses": null,
      "fight_url": null,
      "segment": "prelims"
    },
    {
      "bout_order": 5,
      "fighter1": {
        "name": "Joanderson Brito",
        "record": null,
        "rank": null,
        "country": null,
        "age": null,
        "height": null,
        "weight": null,
        "reach": null,
        "stance": null,
        "nickname": null,
        "bonus": null
      },
      "fighter2": {
        "name": "Westin Wilson",
        "record": null,
        "rank": null,
        "country": null,
        "age": null,
        "height": null,
        "weight": null,
        "reach": null,
        "stance": null,
        "nickname": null,
        "bonus": null
      },
      "weight_class": "Featherweight",
      "title_fight": "none",
      "method": "KO (punches)",
      "round": null,
      "time": null,
      "winner": "Joanderson Brito",
      "result": null,
      "stats": null,
      "referee": null,
      "bonuses": null,
      "fight_url": null,
      "segment": "prelims"
    },
    {
      "bout_order": 4,
      "fighter1": {
        "name": "Karol Rosa",
        "record": null,
        "rank": null,
        "country": null,
        "age": null,
        "height": null,
        "weight": null,
        "reach": null,
        "stance": null,
        "nickname": null,
        "bonus": null
      },
      "fighter2": {
        "name": "Yana Santos",
        "record": null,
        "rank": null,
        "country": null,
        "age": null,
        "height": null,
        "weight": null,
        "reach": null,
        "stance": null,
        "nickname": null,
        "bonus": null
      },
      "weight_class": "Women's Featherweight",
      "title_fight": "none",
      "method": "Decision (split) (28–29, 29–28, 29–28)",
      "round": null,
      "time": null,
      "winner": "Karol Rosa",
      "result": null,
      "stats": null,
      "referee": null,
      "bonuses": null,
      "fight_url": null,
      "segment": "prelims"
    },
    {
      "bout_order": 3,
      "fighter1": {
        "name": "Elves Brener",
        "record": null,
        "rank": null,
        "country": null,
        "age": null,
        "height": null,
        "weight": null,
        "reach": null,
        "stance": null,
        "nickname": null,
        "bonus": null
      },
      "fighter2": {
        "name": "Guram Kutateladze",
        "record": null,
        "rank": null,
        "country": null,
        "age": null,
        "height": null,
        "weight": null,
        "reach": null,
        "stance": null,
        "nickname": null,
        "bonus": null
      },
      "weight_class": "Lightweight",
      "title_fight": "none",
      "method": "TKO (punches)",
      "round": null,
      "time": null,
      "winner": "Elves Brener",
      "result": null,
      "stats": null,
      "referee": null,
      "bonuses": null,
      "fight_url": null,
      "segment": "prelims"
    },
    {
      "bout_order": 2,
      "fighter1": {
        "name": "Luana Carolina",
        "record": null,
        "rank": null,
        "country": null,
        "age": null,
        "height": null,
        "weight": null,
        "reach": null,
        "stance": null,
        "nickname": null,
        "bonus": null
      },
      "fighter2": {
        "name": "Ivana Petrović",
        "record": null,
        "rank": null,
        "country": null,
        "age": null,
        "height": null,
        "weight": null,
        "reach": null,
        "stance": null,
        "nickname": null,
        "bonus": null
      },
      "weight_class": "Women's Flyweight",
      "title_fight": "none",
      "method": "Decision (unanimous) (29–28, 29–28, 29–28)",
      "round": null,
      "time": null,
      "winner": "Luana Carolina",
      "result": null,
      "stats": null,
      "referee": null,
      "bonuses": null,
      "fight_url": null,
      "segment": "prelims"
    },
    {
      "bout_order": 1,
      "fighter1": {
        "name": "Alexander Romanov",
        "record": null,
        "rank": null,
        "country": null,
        "age": null,
        "height": null,
        "weight": null,
        "reach": null,
        "stance": null,
        "nickname": null,
        "bonus": null
      },
      "fighter2": {
        "name": "Blagoy Ivanov",
        "record": null,
        "rank": null,
        "country": null,
        "age": null,
        "height": null,
        "weight": null,
        "reach": null,
        "stance": null,
        "nickname": null,
        "bonus": null
      },
      "weight_class": "Heavyweight",
      "title_fight": "none",
      "method": "Decision (unanimous) (30–27, 30–27, 30–27)",
      "round": null,
      "time": null,
      "winner": "Alexander Romanov",
      "result": null,
      "stats": null,
      "referee": null,
      "bonuses": null,
      "fight_url": null,
      "segment": "prelims"
    }
  ],
  "scraped_at": "2025-07-12T22:38:57.649053",
  "source_urls": {
    "wikipedia": "https://en.wikipedia.org/wiki/UFC_on_ESPN:_Strickland_vs._Magomedov"
  }
}