{
  "event_id": "UFC_304",
  "event_name": "UFC 304",
  "event_date": "2024-07-27",
  "venue": "Co-op Live",
  "location": null,
  "status": "completed",
  "attendance": null,
  "gate": null,
  "tv_broadcast": null,
  "start_time": null,
  "fights": [
    {
      "bout_order": 14,
      "fighter1": {
        "name": "Belal Muhammad",
        "record": null,
        "rank": null,
        "country": null,
        "age": null,
        "height": null,
        "weight": null,
        "reach": null,
        "stance": null,
        "nickname": null,
        "bonus": null,
        "is_champion": false
      },
      "fighter2": {
        "name": "Leon Edwards",
        "record": null,
        "rank": null,
        "country": null,
        "age": null,
        "height": null,
        "weight": null,
        "reach": null,
        "stance": null,
        "nickname": null,
        "bonus": null,
        "is_champion": true
      },
      "weight_class": "Welterweight",
      "title_fight": "undisputed",
      "method": "Decision (unanimous) (48–47, 48–47, 49–46)",
      "round": null,
      "time": null,
      "winner": "Belal Muhammad",
      "result": null,
      "stats": null,
      "referee": null,
      "bonuses": null,
      "fight_url": null,
      "segment": "main-card"
    },
    {
      "bout_order": 13,
      "fighter1": {
        "name": "Tom Aspinall",
        "record": null,
        "rank": null,
        "country": null,
        "age": null,
        "height": null,
        "weight": null,
        "reach": null,
        "stance": null,
        "nickname": null,
        "bonus": null,
        "is_champion": false
      },
      "fighter2": {
        "name": "Curtis Blaydes",
        "record": null,
        "rank": null,
        "country": null,
        "age": null,
        "height": null,
        "weight": null,
        "reach": null,
        "stance": null,
        "nickname": null,
        "bonus": null,
        "is_champion": false
      },
      "weight_class": "Heavyweight",
      "title_fight": "none",
      "method": "KO (punches)",
      "round": null,
      "time": null,
      "winner": "Tom Aspinall",
      "result": null,
      "stats": null,
      "referee": null,
      "bonuses": null,
      "fight_url": null,
      "segment": "main-card"
    },
    {
      "bout_order": 12,
      "fighter1": {
        "name": "Paddy Pimblett",
        "record": null,
        "rank": null,
        "country": null,
        "age": null,
        "height": null,
        "weight": null,
        "reach": null,
        "stance": null,
        "nickname": null,
        "bonus": null,
        "is_champion": false
      },
      "fighter2": {
        "name": "King Green",
        "record": null,
        "rank": null,
        "country": null,
        "age": null,
        "height": null,
        "weight": null,
        "reach": null,
        "stance": null,
        "nickname": null,
        "bonus": null,
        "is_champion": false
      },
      "weight_class": "Lightweight",
      "title_fight": "none",
      "method": "Technical Submission (triangle choke)",
      "round": null,
      "time": null,
      "winner": "Paddy Pimblett",
      "result": null,
      "stats": null,
      "referee": null,
      "bonuses": null,
      "fight_url": null,
      "segment": "main-card"
    },
    {
      "bout_order": 11,
      "fighter1": {
        "name": "Gregory Rodrigues",
        "record": null,
        "rank": null,
        "country": null,
        "age": null,
        "height": null,
        "weight": null,
        "reach": null,
        "stance": null,
        "nickname": null,
        "bonus": null,
        "is_champion": false
      },
      "fighter2": {
        "name": "Christian Leroy Duncan",
        "record": null,
        "rank": null,
        "country": null,
        "age": null,
        "height": null,
        "weight": null,
        "reach": null,
        "stance": null,
        "nickname": null,
        "bonus": null,
        "is_champion": false
      },
      "weight_class": "Middleweight",
      "title_fight": "none",
      "method": "Decision (unanimous) (30–27, 30–27, 30–27)",
      "round": null,
      "time": null,
      "winner": "Gregory Rodrigues",
      "result": null,
      "stats": null,
      "referee": null,
      "bonuses": null,
      "fight_url": null,
      "segment": "main-card"
    },
    {
      "bout_order": 10,
      "fighter1": {
        "name": "Arnold Allen",
        "record": null,
        "rank": null,
        "country": null,
        "age": null,
        "height": null,
        "weight": null,
        "reach": null,
        "stance": null,
        "nickname": null,
        "bonus": null,
        "is_champion": false
      },
      "fighter2": {
        "name": "Giga Chikadze",
        "record": null,
        "rank": null,
        "country": null,
        "age": null,
        "height": null,
        "weight": null,
        "reach": null,
        "stance": null,
        "nickname": null,
        "bonus": null,
        "is_champion": false
      },
      "weight_class": "Featherweight",
      "title_fight": "none",
      "method": "Decision (unanimous) (29–28, 29–28, 29–28)",
      "round": null,
      "time": null,
      "winner": "Arnold Allen",
      "result": null,
      "stats": null,
      "referee": null,
      "bonuses": null,
      "fight_url": null,
      "segment": "main-card"
    },
    {
      "bout_order": 9,
      "fighter1": {
        "name": "Nathaniel Wood",
        "record": null,
        "rank": null,
        "country": null,
        "age": null,
        "height": null,
        "weight": null,
        "reach": null,
        "stance": null,
        "nickname": null,
        "bonus": null,
        "is_champion": false
      },
      "fighter2": {
        "name": "Daniel Pineda",
        "record": null,
        "rank": null,
        "country": null,
        "age": null,
        "height": null,
        "weight": null,
        "reach": null,
        "stance": null,
        "nickname": null,
        "bonus": null,
        "is_champion": false
      },
      "weight_class": "Featherweight",
      "title_fight": "none",
      "method": "Decision (unanimous) (29–27, 29–27, 29–28)",
      "round": null,
      "time": null,
      "winner": "Nathaniel Wood",
      "result": null,
      "stats": null,
      "referee": null,
      "bonuses": null,
      "fight_url": null,
      "segment": "prelims"
    },
    {
      "bout_order": 8,
      "fighter1": {
        "name": "Bruna Brasil",
        "record": null,
        "rank": null,
        "country": null,
        "age": null,
        "height": null,
        "weight": null,
        "reach": null,
        "stance": null,
        "nickname": null,
        "bonus": null,
        "is_champion": false
      },
      "fighter2": {
        "name": "Molly McCann",
        "record": null,
        "rank": null,
        "country": null,
        "age": null,
        "height": null,
        "weight": null,
        "reach": null,
        "stance": null,
        "nickname": null,
        "bonus": null,
        "is_champion": false
      },
      "weight_class": "Women's Strawweight",
      "title_fight": "none",
      "method": "Decision (unanimous) (30–27, 30–27, 29–28)",
      "round": null,
      "time": null,
      "winner": "Bruna Brasil",
      "result": null,
      "stats": null,
      "referee": null,
      "bonuses": null,
      "fight_url": null,
      "segment": "prelims"
    },
    {
      "bout_order": 7,
      "fighter1": {
        "name": "Jake Hadley",
        "record": null,
        "rank": null,
        "country": null,
        "age": null,
        "height": null,
        "weight": null,
        "reach": null,
        "stance": null,
        "nickname": null,
        "bonus": null,
        "is_champion": false
      },
      "fighter2": {
        "name": "Caolán Loughran",
        "record": null,
        "rank": null,
        "country": null,
        "age": null,
        "height": null,
        "weight": null,
        "reach": null,
        "stance": null,
        "nickname": null,
        "bonus": null,
        "is_champion": false
      },
      "weight_class": "Catchweight (137 lb)",
      "title_fight": "none",
      "method": "Decision (unanimous) (30–27, 30–27, 29–28)",
      "round": null,
      "time": null,
      "winner": "Jake Hadley",
      "result": null,
      "stats": null,
      "referee": null,
      "bonuses": null,
      "fight_url": null,
      "segment": "prelims"
    },
    {
      "bout_order": 6,
      "fighter1": {
        "name": "Muhammad Mokaev",
        "record": null,
        "rank": null,
        "country": null,
        "age": null,
        "height": null,
        "weight": null,
        "reach": null,
        "stance": null,
        "nickname": null,
        "bonus": null,
        "is_champion": false
      },
      "fighter2": {
        "name": "Manel Kape",
        "record": null,
        "rank": null,
        "country": null,
        "age": null,
        "height": null,
        "weight": null,
        "reach": null,
        "stance": null,
        "nickname": null,
        "bonus": null,
        "is_champion": false
      },
      "weight_class": "Flyweight",
      "title_fight": "none",
      "method": "Decision (unanimous) (29–28, 29–28, 30–27)",
      "round": null,
      "time": null,
      "winner": "Muhammad Mokaev",
      "result": null,
      "stats": null,
      "referee": null,
      "bonuses": null,
      "fight_url": null,
      "segment": "prelims"
    },
    {
      "bout_order": 5,
      "fighter1": {
        "name": "Oban Elliott",
        "record": null,
        "rank": null,
        "country": null,
        "age": null,
        "height": null,
        "weight": null,
        "reach": null,
        "stance": null,
        "nickname": null,
        "bonus": null,
        "is_champion": false
      },
      "fighter2": {
        "name": "Preston Parsons",
        "record": null,
        "rank": null,
        "country": null,
        "age": null,
        "height": null,
        "weight": null,
        "reach": null,
        "stance": null,
        "nickname": null,
        "bonus": null,
        "is_champion": false
      },
      "weight_class": "Welterweight",
      "title_fight": "none",
      "method": "Decision (unanimous) (29–28, 30–27, 30–27)",
      "round": null,
      "time": null,
      "winner": "Oban Elliott",
      "result": null,
      "stats": null,
      "referee": null,
      "bonuses": null,
      "fight_url": null,
      "segment": "early-prelims"
    },
    {
      "bout_order": 4,
      "fighter1": {
        "name": "Modestas Bukauskas",
        "record": null,
        "rank": null,
        "country": null,
        "age": null,
        "height": null,
        "weight": null,
        "reach": null,
        "stance": null,
        "nickname": null,
        "bonus": null,
        "is_champion": false
      },
      "fighter2": {
        "name": "Marcin Prachnio",
        "record": null,
        "rank": null,
        "country": null,
        "age": null,
        "height": null,
        "weight": null,
        "reach": null,
        "stance": null,
        "nickname": null,
        "bonus": null,
        "is_champion": false
      },
      "weight_class": "Light Heavyweight",
      "title_fight": "none",
      "method": "Submission (arm-triangle choke)",
      "round": null,
      "time": null,
      "winner": "Modestas Bukauskas",
      "result": null,
      "stats": null,
      "referee": null,
      "bonuses": null,
      "fight_url": null,
      "segment": "early-prelims"
    },
    {
      "bout_order": 3,
      "fighter1": {
        "name": "Sam Patterson",
        "record": null,
        "rank": null,
        "country": null,
        "age": null,
        "height": null,
        "weight": null,
        "reach": null,
        "stance": null,
        "nickname": null,
        "bonus": null,
        "is_champion": false
      },
      "fighter2": {
        "name": "Kiefer Crosbie",
        "record": null,
        "rank": null,
        "country": null,
        "age": null,
        "height": null,
        "weight": null,
        "reach": null,
        "stance": null,
        "nickname": null,
        "bonus": null,
        "is_champion": false
      },
      "weight_class": "Welterweight",
      "title_fight": "none",
      "method": "Submission (arm-triangle choke)",
      "round": null,
      "time": null,
      "winner": "Sam Patterson",
      "result": null,
      "stats": null,
      "referee": null,
      "bonuses": null,
      "fight_url": null,
      "segment": "early-prelims"
    },
    {
      "bout_order": 2,
      "fighter1": {
        "name": "Mick Parkin",
        "record": null,
        "rank": null,
        "country": null,
        "age": null,
        "height": null,
        "weight": null,
        "reach": null,
        "stance": null,
        "nickname": null,
        "bonus": null,
        "is_champion": false
      },
      "fighter2": {
        "name": "Łukasz Brzeski",
        "record": null,
        "rank": null,
        "country": null,
        "age": null,
        "height": null,
        "weight": null,
        "reach": null,
        "stance": null,
        "nickname": null,
        "bonus": null,
        "is_champion": false
      },
      "weight_class": "Heavyweight",
      "title_fight": "none",
      "method": "KO (punches)",
      "round": null,
      "time": null,
      "winner": "Mick Parkin",
      "result": null,
      "stats": null,
      "referee": null,
      "bonuses": null,
      "fight_url": null,
      "segment": "early-prelims"
    },
    {
      "bout_order": 1,
      "fighter1": {
        "name": "Shauna Bannon",
        "record": null,
        "rank": null,
        "country": null,
        "age": null,
        "height": null,
        "weight": null,
        "reach": null,
        "stance": null,
        "nickname": null,
        "bonus": null,
        "is_champion": false
      },
      "fighter2": {
        "name": "Alice Ardelean",
        "record": null,
        "rank": null,
        "country": null,
        "age": null,
        "height": null,
        "weight": null,
        "reach": null,
        "stance": null,
        "nickname": null,
        "bonus": null,
        "is_champion": false
      },
      "weight_class": "Women's Strawweight",
      "title_fight": "none",
      "method": "Decision (split) (28–29, 29–28, 30–27)",
      "round": null,
      "time": null,
      "winner": "Shauna Bannon",
      "result": null,
      "stats": null,
      "referee": null,
      "bonuses": null,
      "fight_url": null,
      "segment": "early-prelims"
    }
  ],
  "scraped_at": "2025-07-13T11:48:42.399654",
  "source_urls": {
    "wikipedia": "https://en.wikipedia.org/wiki/UFC_304"
  }
}